{
  "info": {
    "id": "mptvf7fVEL",
    "title": "Dystopic Worlds",
    "description": "A serie inspired by abstract and futuristic dystopic world artworks.",
    "cover_uri": "",
    "private": false,
    "user": {
      "id": "tz1fFQ6BVqcQk2gK1uCUmTMJ5cGdhQfraWdH",
      "name": "tz1fFQ6BVqcQk2gK1uCUmTMJ5cGdhQfraWdH",
      "profile_image_uri": "ipfs://bafkreidepn5tfkqqqaaeo3rv47atqnwyg3el4b75qzhvu252yqj75vuyh4",
      "verified": true,
      "verified_on_chain": true,
      "screen_name": "Trips"
    },
    "tokens": [
      {
        "token": {
          "id": "f35d3d869175beab32c550f227fb1f1b9dd3478160203d676f07791d1e057cd4",
          "formats": [
            {
              "uri": "ipfs://QmPpicQQEkVy4i9kRJSL4Dmat1pX69L8aCpDtWdKA24jXa",
              "fileName": "original.png",
              "fileSize": 29237386,
              "mimeType": "image/png",
              "dimensions": {
                "unit": "px",
                "value": "2400x2400"
              }
            },
            {
              "uri": "ipfs://QmeyVc25JfGxUAK7YCAQHYEdC42thSmWJ4HUAViGXb5c8P",
              "fileName": "preview_image_2048w.jpg",
              "fileSize": 345645,
              "mimeType": "image/jpeg",
              "dimensions": {
                "unit": "px",
                "value": "2048x2048"
              }
            },
            {
              "uri": "ipfs://QmPdK37Ycs9pXcuGuLzcTmbLaLJLHs6Ww4n7o1pNbss5iS",
              "fileName": "preview_image_1024w.jpg",
              "fileSize": 129591,
              "mimeType": "image/jpeg",
              "dimensions": {
                "unit": "px",
                "value": "1024x1024"
              }
            },
            {
              "uri": "ipfs://Qme4LPQbxDjiFuKQJoEMPsqtc8qgqXC43SRtRMUDi956as",
              "fileName": "preview_image_960w.jpg",
              "fileSize": 117970,
              "mimeType": "image/jpeg",
              "dimensions": {
                "unit": "px",
                "value": "960x960"
              }
            },
            {
              "uri": "ipfs://QmUtmyuC9GZpoZT8RR2z7AmyjfnmSBhVSdym754NxQKmkC",
              "fileName": "preview_image_480w.jpg",
              "fileSize": 42208,
              "mimeType": "image/jpeg",
              "dimensions": {
                "unit": "px",
                "value": "480x480"
              }
            }
          ]
        }
      },
      {
        "token": {
          "id": "0ba4ae4dd075b97a051d56795d5912d30fe7bbe90c4d4b83dee5a69c31877937",
          "formats": [
            {
              "uri": "ipfs://QmbxwyS9qNaGGEo24Z2uwm9F9ZjfYT177DTDgWg65scGXZ",
              "fileName": "original.png",
              "fileSize": 19872550,
              "mimeType": "image/png",
              "dimensions": {
                "unit": "px",
                "value": "3840x1680"
              }
            },
            {
              "uri": "ipfs://QmeCaH44kRVDUk6waGJ9YGebVEQQfeivsh8ALbPoN2bgsj",
              "fileName": "preview_image_2048w.jpg",
              "fileSize": 182563,
              "mimeType": "image/jpeg",
              "dimensions": {
                "unit": "px",
                "value": "2048x896"
              }
            },
            {
              "uri": "ipfs://QmQfVMgqFt6587mvUhCBsfnuTcX5ZN8GfuTFHe9U7tA9v5",
              "fileName": "preview_image_1024w.jpg",
              "fileSize": 62506,
              "mimeType": "image/jpeg",
              "dimensions": {
                "unit": "px",
                "value": "1024x448"
              }
            },
            {
              "uri": "ipfs://QmbzB9C2d5JwXEawhrPRkCB1GJFyWQwmLLeBqnRyqcoCAT",
              "fileName": "preview_image_960w.jpg",
              "fileSize": 56630,
              "mimeType": "image/jpeg",
              "dimensions": {
                "unit": "px",
                "value": "960x420"
              }
            },
            {
              "uri": "ipfs://QmRboqtg1QrzB7kXDtNX13e5jDQG5A86qnPMRQbnn5JYu4",
              "fileName": "preview_image_480w.jpg",
              "fileSize": 18926,
              "mimeType": "image/jpeg",
              "dimensions": {
                "unit": "px",
                "value": "480x210"
              }
            }
          ]
        }
      },
      {
        "token": {
          "id": "e55c8cae9d653142ac5bd899d1044eab533d6f3892a4c5e0130f1c94948d0329",
          "formats": [
            {
              "uri": "ipfs://Qmbh9cV7qf52nC8u5DgNr1T93cYFyNWTdVHRJSqLm3xpSh",
              "fileName": "original.png",
              "fileSize": 14240726,
              "mimeType": "image/png",
              "dimensions": {
                "unit": "px",
                "value": "2400x2400"
              }
            },
            {
              "uri": "ipfs://QmU5DDu31i7ETPRktAWmrgo7jp9HrQe4V4UZaxT9aPKYCa",
              "fileName": "preview_image_2048w.jpg",
              "fileSize": 461154,
              "mimeType": "image/jpeg",
              "dimensions": {
                "unit": "px",
                "value": "2048x2048"
              }
            },
            {
              "uri": "ipfs://QmSFDrJHLFG6PgL6d6PXhv1jX9Edb9BLYdAKr1QdFmAnxU",
              "fileName": "preview_image_1024w.jpg",
              "fileSize": 151057,
              "mimeType": "image/jpeg",
              "dimensions": {
                "unit": "px",
                "value": "1024x1024"
              }
            },
            {
              "uri": "ipfs://QmZCABT5kv6w2KDjwt6MnPpgDoDW9AW9qSLty5LNEjr6e2",
              "fileName": "preview_image_960w.jpg",
              "fileSize": 136208,
              "mimeType": "image/jpeg",
              "dimensions": {
                "unit": "px",
                "value": "960x960"
              }
            },
            {
              "uri": "ipfs://QmSMVBo3TPCMFPoAo8ix2qC2zYfPM9fRG2ZjwXok6rxXax",
              "fileName": "preview_image_480w.jpg",
              "fileSize": 40992,
              "mimeType": "image/jpeg",
              "dimensions": {
                "unit": "px",
                "value": "480x480"
              }
            }
          ]
        }
      },
      {
        "token": {
          "id": "0ec15fa087ffa3d52998bbfbe5323e41907df2a4e0f27002e1c6353f9f5cb8c9",
          "formats": [
            {
              "uri": "ipfs://QmVJ1kr5xSGoJNdYMqairKxhwubkPXVoQvKCP6Hb4aiKVv",
              "fileName": "original.png",
              "fileSize": 71040460,
              "mimeType": "image/png",
              "dimensions": {
                "unit": "px",
                "value": "8000x4000"
              }
            },
            {
              "uri": "ipfs://QmULMK48dSBPmURQgWBASzaxmiDNXWzKg3SZHVMEVYrx8R",
              "fileName": "preview_image_2048w.jpg",
              "fileSize": 588400,
              "mimeType": "image/jpeg",
              "dimensions": {
                "unit": "px",
                "value": "2048x1024"
              }
            },
            {
              "uri": "ipfs://QmNfcaf2wGsPzhmEG85sVaCk94Pp9KBAzpqWS8JWwBNcCj",
              "fileName": "preview_image_1024w.jpg",
              "fileSize": 158794,
              "mimeType": "image/jpeg",
              "dimensions": {
                "unit": "px",
                "value": "1024x512"
              }
            },
            {
              "uri": "ipfs://QmYoaf2QYWNiGGrhfVBLQDFZxSWpK45jhy6BVDS6u6RN5d",
              "fileName": "preview_image_960w.jpg",
              "fileSize": 140249,
              "mimeType": "image/jpeg",
              "dimensions": {
                "unit": "px",
                "value": "960x480"
              }
            },
            {
              "uri": "ipfs://QmZoUK1g9n9h6942KQAKMHiNBRSYjNSGX3ii7Trbnv25xH",
              "fileName": "preview_image_480w.jpg",
              "fileSize": 38208,
              "mimeType": "image/jpeg",
              "dimensions": {
                "unit": "px",
                "value": "480x240"
              }
            }
          ]
        }
      }
    ]
  },
  "tokens": [
    {
      "contract": "KT1LjmAdYQCLBjwv4S2oFkEzyHVkomAf5MrW",
      "tokenId": 25637
    },
    {
      "contract": "KT1LjmAdYQCLBjwv4S2oFkEzyHVkomAf5MrW",
      "tokenId": 25297
    },
    {
      "contract": "KT1LjmAdYQCLBjwv4S2oFkEzyHVkomAf5MrW",
      "tokenId": 24913
    },
    {
      "contract": "KT1LjmAdYQCLBjwv4S2oFkEzyHVkomAf5MrW",
      "tokenId": 19792
    },
    {
      "contract": "KT1LjmAdYQCLBjwv4S2oFkEzyHVkomAf5MrW",
      "tokenId": 19731
    },
    {
      "contract": "KT1LjmAdYQCLBjwv4S2oFkEzyHVkomAf5MrW",
      "tokenId": 19525
    },
    {
      "contract": "KT1LjmAdYQCLBjwv4S2oFkEzyHVkomAf5MrW",
      "tokenId": 19212
    },
    {
      "contract": "KT1LjmAdYQCLBjwv4S2oFkEzyHVkomAf5MrW",
      "tokenId": 18986
    },
    {
      "contract": "KT1LjmAdYQCLBjwv4S2oFkEzyHVkomAf5MrW",
      "tokenId": 18631
    },
    {
      "contract": "KT1LjmAdYQCLBjwv4S2oFkEzyHVkomAf5MrW",
      "tokenId": 18369
    },
    {
      "contract": "KT1LjmAdYQCLBjwv4S2oFkEzyHVkomAf5MrW",
      "tokenId": 18287
    },
    {
      "contract": "KT1LjmAdYQCLBjwv4S2oFkEzyHVkomAf5MrW",
      "tokenId": 13479
    },
    {
      "contract": "KT1LjmAdYQCLBjwv4S2oFkEzyHVkomAf5MrW",
      "tokenId": 13176
    }
  ]
}