{
  "info": {
    "id": "VXtDfRfa26",
    "title": "Loneliness by Farbod Rostami",
    "description": "Loneliness, the only reality of life!",
    "cover_uri": "ipfs://QmQf2XXZM9EwKeqUqpQ41xHA2xyqQYuQKynJG71hufFYuW",
    "private": false,
    "user": {
      "id": "tz1Ny5BVF6k9Kfi7TJtwS5b28QqME6wcqbeP",
      "name": "tz1Ny5BVF6k9Kfi7TJtwS5b28QqME6wcqbeP",
      "profile_image_uri": "ipfs://QmZzbkbKmJo5UT87ZuvzMhvKGFH7eDZMKtFtPiRm39DfPc",
      "verified": true,
      "verified_on_chain": true,
      "screen_name": "Farbod Rostami"
    },
    "tokens": []
  },
  "tokens": []
}