{
  "info": {
    "id": "G5t7f5f5qY",
    "title": "Y2 Revolutionary Happiness",
    "description": "OG's and noobs remix the original in Y2 of our ongoing project. ",
    "cover_uri": null,
    "private": false,
    "user": {
      "id": "tz1NHP2mmBNbagWLLnaKM3C1QCtmuk2Qjg26",
      "name": "tz1NHP2mmBNbagWLLnaKM3C1QCtmuk2Qjg26",
      "profile_image_uri": "ipfs://QmdwxxzdFijh4rnCdHtRU5ovy4UaMggGK7FsxmxRtWcu7U",
      "verified": true,
      "verified_on_chain": true,
      "screen_name": "LabelsOnHumans"
    },
    "tokens": [
      {
        "token": {
          "id": "e8a0c342657d64b9a6a86b0332707e9ee64ebb83ceaaf68cb653d27c3b452ef7",
          "formats": [
            {
              "uri": "ipfs://bafybeibzgid6zeexoctyiaqzfdfgggpd55czjvnv72e5iq7ju3fkkzulom",
              "fileName": "original.png",
              "fileSize": 60623416,
              "mimeType": "image/png",
              "dimensions": {
                "unit": "px",
                "value": "4950x7050"
              }
            },
            {
              "uri": "ipfs://bafybeiej2wsdvauoznudcexzypgqym2pczkd2x4y5aluvzgx2mdotlxuwm/media/preview_image_2048w.jpg",
              "fileName": "preview_image_2048w.jpg",
              "fileSize": 1724426,
              "mimeType": "image/jpeg",
              "dimensions": {
                "unit": "px",
                "value": "2048x2917"
              }
            },
            {
              "uri": "ipfs://bafybeiej2wsdvauoznudcexzypgqym2pczkd2x4y5aluvzgx2mdotlxuwm/media/preview_image_1024w.jpg",
              "fileName": "preview_image_1024w.jpg",
              "fileSize": 592547,
              "mimeType": "image/jpeg",
              "dimensions": {
                "unit": "px",
                "value": "1024x1458"
              }
            },
            {
              "uri": "ipfs://bafybeiej2wsdvauoznudcexzypgqym2pczkd2x4y5aluvzgx2mdotlxuwm/media/preview_image_960w.jpg",
              "fileName": "preview_image_960w.jpg",
              "fileSize": 536533,
              "mimeType": "image/jpeg",
              "dimensions": {
                "unit": "px",
                "value": "960x1367"
              }
            },
            {
              "uri": "ipfs://bafybeiej2wsdvauoznudcexzypgqym2pczkd2x4y5aluvzgx2mdotlxuwm/media/preview_image_480w.jpg",
              "fileName": "preview_image_480w.jpg",
              "fileSize": 162943,
              "mimeType": "image/jpeg",
              "dimensions": {
                "unit": "px",
                "value": "480x684"
              }
            }
          ]
        }
      },
      {
        "token": {
          "id": "f007d5c4341db321f1aa5d7fd058d4b38554c80c192c8fdef0a6fccc617c3786",
          "formats": [
            {
              "uri": "ipfs://bafybeidr27xyvuqbl7nl2ihy2ffn24j2klpbbvx72wwhz2pl56giv7vxhe",
              "fileName": "original.png",
              "fileSize": 31674533,
              "mimeType": "image/png",
              "dimensions": {
                "unit": "px",
                "value": "7050x4950"
              }
            },
            {
              "uri": "ipfs://bafybeidlszmovnqc2dop2z35w2b6hcqhhe63gfkdhjtyraxxkeapu2bldu/media/preview_image_2048w.jpg",
              "fileName": "preview_image_2048w.jpg",
              "fileSize": 391298,
              "mimeType": "image/jpeg",
              "dimensions": {
                "unit": "px",
                "value": "2048x1438"
              }
            },
            {
              "uri": "ipfs://bafybeidlszmovnqc2dop2z35w2b6hcqhhe63gfkdhjtyraxxkeapu2bldu/media/preview_image_1024w.jpg",
              "fileName": "preview_image_1024w.jpg",
              "fileSize": 127907,
              "mimeType": "image/jpeg",
              "dimensions": {
                "unit": "px",
                "value": "1024x719"
              }
            },
            {
              "uri": "ipfs://bafybeidlszmovnqc2dop2z35w2b6hcqhhe63gfkdhjtyraxxkeapu2bldu/media/preview_image_960w.jpg",
              "fileName": "preview_image_960w.jpg",
              "fileSize": 116337,
              "mimeType": "image/jpeg",
              "dimensions": {
                "unit": "px",
                "value": "960x674"
              }
            },
            {
              "uri": "ipfs://bafybeidlszmovnqc2dop2z35w2b6hcqhhe63gfkdhjtyraxxkeapu2bldu/media/preview_image_480w.jpg",
              "fileName": "preview_image_480w.jpg",
              "fileSize": 39884,
              "mimeType": "image/jpeg",
              "dimensions": {
                "unit": "px",
                "value": "480x337"
              }
            }
          ]
        }
      },
      {
        "token": {
          "id": "acfb098bad31e2d498a80784489ca5f91edc1b4a9816343c8861c4cf0193bc0f",
          "formats": [
            {
              "uri": "ipfs://bafybeiagrsrdwlvckrfiuhzlm6pgx3aaavwytv3ewgm3pwtdcrcgqm4lbu",
              "fileName": "original.png",
              "fileSize": 24124849,
              "mimeType": "image/png",
              "dimensions": {
                "unit": "px",
                "value": "4593x4950"
              }
            },
            {
              "uri": "ipfs://bafybeicedhzgabbpyxi3nlr25lcbye2a56scwnrq757kb3mdardgpn6etq/media/preview_image_2048w.jpg",
              "fileName": "preview_image_2048w.jpg",
              "fileSize": 769617,
              "mimeType": "image/jpeg",
              "dimensions": {
                "unit": "px",
                "value": "2048x2207"
              }
            },
            {
              "uri": "ipfs://bafybeicedhzgabbpyxi3nlr25lcbye2a56scwnrq757kb3mdardgpn6etq/media/preview_image_1024w.jpg",
              "fileName": "preview_image_1024w.jpg",
              "fileSize": 333164,
              "mimeType": "image/jpeg",
              "dimensions": {
                "unit": "px",
                "value": "1024x1104"
              }
            },
            {
              "uri": "ipfs://bafybeicedhzgabbpyxi3nlr25lcbye2a56scwnrq757kb3mdardgpn6etq/media/preview_image_960w.jpg",
              "fileName": "preview_image_960w.jpg",
              "fileSize": 306718,
              "mimeType": "image/jpeg",
              "dimensions": {
                "unit": "px",
                "value": "960x1035"
              }
            },
            {
              "uri": "ipfs://bafybeicedhzgabbpyxi3nlr25lcbye2a56scwnrq757kb3mdardgpn6etq/media/preview_image_480w.jpg",
              "fileName": "preview_image_480w.jpg",
              "fileSize": 118590,
              "mimeType": "image/jpeg",
              "dimensions": {
                "unit": "px",
                "value": "480x517"
              }
            }
          ]
        }
      },
      {
        "token": {
          "id": "b7162f823a3a6339d5cd0b62057eded60d38297f98fd35a632add394b3d93d2e",
          "formats": [
            {
              "uri": "ipfs://bafybeihaoajsw34wsxvejckk4bp75ek6cblk5d25zocnrdmuszp7vriq3y/media/full_video_720h.mp4",
              "duration": "00:00:20.544000",
              "fileName": "full_video_720h.mp4",
              "fileSize": 9858941,
              "mimeType": "video/mp4",
              "dimensions": {
                "unit": "px",
                "value": "720x720"
              }
            },
            {
              "uri": "ipfs://bafybeie4lvq7aw56mi5t5yhijqxf4upsfo7fvsrxc2kpzosy5ivgt37a5y",
              "duration": "00:00:20.533333",
              "fileName": "original.mp4",
              "fileSize": 42796316,
              "mimeType": "video/mp4",
              "dimensions": {
                "unit": "px",
                "value": "1280x1280"
              }
            },
            {
              "uri": "ipfs://bafybeihaoajsw34wsxvejckk4bp75ek6cblk5d25zocnrdmuszp7vriq3y/media/preview_video_480w.mp4",
              "duration": "00:00:20.000000",
              "fileName": "preview_video_480w.mp4",
              "fileSize": 3406729,
              "mimeType": "video/mp4",
              "dimensions": {
                "unit": "px",
                "value": "480x480"
              }
            },
            {
              "uri": "ipfs://bafybeihaoajsw34wsxvejckk4bp75ek6cblk5d25zocnrdmuszp7vriq3y/media/preview_image_1280w.jpg",
              "fileName": "preview_image_1280w.jpg",
              "fileSize": 419372,
              "mimeType": "image/jpeg",
              "dimensions": {
                "unit": "px",
                "value": "1280x1280"
              }
            },
            {
              "uri": "ipfs://bafybeihaoajsw34wsxvejckk4bp75ek6cblk5d25zocnrdmuszp7vriq3y/media/preview_image_1024w.jpg",
              "fileName": "preview_image_1024w.jpg",
              "fileSize": 254333,
              "mimeType": "image/jpeg",
              "dimensions": {
                "unit": "px",
                "value": "1024x1024"
              }
            },
            {
              "uri": "ipfs://bafybeihaoajsw34wsxvejckk4bp75ek6cblk5d25zocnrdmuszp7vriq3y/media/preview_image_960w.jpg",
              "fileName": "preview_image_960w.jpg",
              "fileSize": 224621,
              "mimeType": "image/jpeg",
              "dimensions": {
                "unit": "px",
                "value": "960x960"
              }
            },
            {
              "uri": "ipfs://bafybeihaoajsw34wsxvejckk4bp75ek6cblk5d25zocnrdmuszp7vriq3y/media/preview_image_480w.jpg",
              "fileName": "preview_image_480w.jpg",
              "fileSize": 52172,
              "mimeType": "image/jpeg",
              "dimensions": {
                "unit": "px",
                "value": "480x480"
              }
            }
          ]
        }
      }
    ]
  },
  "tokens": [
    {
      "contract": "KT1LjmAdYQCLBjwv4S2oFkEzyHVkomAf5MrW",
      "tokenId": 33898
    },
    {
      "contract": "KT1LjmAdYQCLBjwv4S2oFkEzyHVkomAf5MrW",
      "tokenId": 33876
    },
    {
      "contract": "KT1LjmAdYQCLBjwv4S2oFkEzyHVkomAf5MrW",
      "tokenId": 33729
    },
    {
      "contract": "KT1LjmAdYQCLBjwv4S2oFkEzyHVkomAf5MrW",
      "tokenId": 33706
    },
    {
      "contract": "KT1LjmAdYQCLBjwv4S2oFkEzyHVkomAf5MrW",
      "tokenId": 33618
    },
    {
      "contract": "KT1LjmAdYQCLBjwv4S2oFkEzyHVkomAf5MrW",
      "tokenId": 33615
    },
    {
      "contract": "KT1LjmAdYQCLBjwv4S2oFkEzyHVkomAf5MrW",
      "tokenId": 33557
    },
    {
      "contract": "KT1LjmAdYQCLBjwv4S2oFkEzyHVkomAf5MrW",
      "tokenId": 33518
    },
    {
      "contract": "KT1LjmAdYQCLBjwv4S2oFkEzyHVkomAf5MrW",
      "tokenId": 33484
    },
    {
      "contract": "KT1LjmAdYQCLBjwv4S2oFkEzyHVkomAf5MrW",
      "tokenId": 33480
    },
    {
      "contract": "KT1LjmAdYQCLBjwv4S2oFkEzyHVkomAf5MrW",
      "tokenId": 33476
    },
    {
      "contract": "KT1LjmAdYQCLBjwv4S2oFkEzyHVkomAf5MrW",
      "tokenId": 33475
    },
    {
      "contract": "KT1LjmAdYQCLBjwv4S2oFkEzyHVkomAf5MrW",
      "tokenId": 33473
    },
    {
      "contract": "KT1LjmAdYQCLBjwv4S2oFkEzyHVkomAf5MrW",
      "tokenId": 33417
    },
    {
      "contract": "KT1LjmAdYQCLBjwv4S2oFkEzyHVkomAf5MrW",
      "tokenId": 33376
    },
    {
      "contract": "KT1LjmAdYQCLBjwv4S2oFkEzyHVkomAf5MrW",
      "tokenId": 33375
    }
  ]
}