{
  "info": {
    "id": "xjtdfVfJg",
    "title": "Wiggle it",
    "description": "Jiggy art collected by @dehiscenceart",
    "cover_uri": "",
    "private": false,
    "user": {
      "id": "tz1TtZmtxhiWc8Nv6AtC1YjVCtJoFjv4nTqL",
      "name": "tz1TtZmtxhiWc8Nv6AtC1YjVCtJoFjv4nTqL",
      "profile_image_uri": "ipfs://QmR6kYoEFpZ5Zasu2yW1VqnQiqwPjv2xwxBSt4eELeDffN",
      "verified": true,
      "verified_on_chain": true,
      "screen_name": "Dehiscence"
    },
    "tokens": [
      {
        "token": {
          "id": "daa6f6cd430c177b0dd151eb299b17bbd117d5ca3eb4697f763ada8ddd0071a4",
          "formats": [
            {
              "uri": "ipfs://QmZkxqGarPJ85RVUvGcJDAmshs8XkzeNrQpgxCjWsCSE6d",
              "duration": "00:00:06.528000",
              "fileName": "original.mp4",
              "fileSize": 40652908,
              "mimeType": "video/mp4",
              "dimensions": {
                "unit": "px",
                "value": "2048x1536"
              }
            },
            {
              "uri": "ipfs://QmVmMbFGVnhCrYapUUwbQ57wnZsfmecQN368ffKnKnGyoF",
              "duration": "00:00:06.528000",
              "fileName": "full_video_720h.mp4",
              "fileSize": 3200609,
              "mimeType": "video/mp4",
              "dimensions": {
                "unit": "px",
                "value": "960x720"
              }
            },
            {
              "uri": "ipfs://Qmb6pc7cvd5Cmyt6J6PDwLWYzxD13yAPmwu44VxpCa7gE2",
              "duration": "00:00:06.528000",
              "fileName": "preview_video_480w.mp4",
              "fileSize": 1051701,
              "mimeType": "video/mp4",
              "dimensions": {
                "unit": "px",
                "value": "480x360"
              }
            },
            {
              "uri": "ipfs://QmP9QjV1Bdp51kqYnvdghbac4nyDPEUgUJwa9smgym6ZzP",
              "fileName": "preview_image_2048w.jpg",
              "fileSize": 358780,
              "mimeType": "image/jpeg",
              "dimensions": {
                "unit": "px",
                "value": "2048x1536"
              }
            },
            {
              "uri": "ipfs://QmeaApEjcVyAUaSf1j3mPsFcP7AZztK5Qs8f8e8aTC7V9n",
              "fileName": "preview_image_1024w.jpg",
              "fileSize": 101732,
              "mimeType": "image/jpeg",
              "dimensions": {
                "unit": "px",
                "value": "1024x768"
              }
            },
            {
              "uri": "ipfs://QmVnLsu6UevXVJfC1WBBsvr25cCw8zLvr3KhwjKqzzEQtq",
              "fileName": "preview_image_960w.jpg",
              "fileSize": 92320,
              "mimeType": "image/jpeg",
              "dimensions": {
                "unit": "px",
                "value": "960x720"
              }
            },
            {
              "uri": "ipfs://Qma5fS2qfx5MVETJGX3NkUgmmtTUERQpeeNTn13FwqHV3x",
              "fileName": "preview_image_480w.jpg",
              "fileSize": 30136,
              "mimeType": "image/jpeg",
              "dimensions": {
                "unit": "px",
                "value": "480x360"
              }
            }
          ]
        }
      },
      {
        "token": {
          "id": "8120c0f54bc2463fff9cb7e728d231244871015df1bb29ff3d5c392b21553468",
          "formats": [
            {
              "uri": "ipfs://QmX11cSDEt5fPoFAa9dnp35av4mWbCciWWmtSWEz54p2CN",
              "duration": "00:00:00.500000",
              "fileName": "original.gif",
              "fileSize": 2557495,
              "mimeType": "image/gif",
              "dimensions": {
                "unit": "px",
                "value": "1500x1056"
              }
            },
            {
              "uri": "ipfs://QmNfUV1GWRuTTPcwAxrnTLjxXbqwgGogTJhc4f9M6SAXCA",
              "fileName": "preview_image_1024w.jpg",
              "fileSize": 321570,
              "mimeType": "image/jpeg",
              "dimensions": {
                "unit": "px",
                "value": "1024x721"
              }
            },
            {
              "uri": "ipfs://QmRdhryJhTveVh5dLrzTs4RcgjDWbJsgsjq3pFfaByYbV3",
              "fileName": "preview_image_960w.jpg",
              "fileSize": 281667,
              "mimeType": "image/jpeg",
              "dimensions": {
                "unit": "px",
                "value": "960x676"
              }
            },
            {
              "uri": "ipfs://QmQCmzUJqJD17tKytMZPZgYvTdVJVd8ySaCTW3Xy9Hkosy",
              "duration": "00:00:00.500000",
              "fileName": "preview_video_480w.mp4",
              "fileSize": 178545,
              "mimeType": "video/mp4",
              "dimensions": {
                "unit": "px",
                "value": "480x338"
              }
            },
            {
              "uri": "ipfs://QmVjAzrmM5Q5yu2wEcnLsG4ctxpsiVWZh9fm9gbMXchZzM",
              "fileName": "preview_image_480w.jpg",
              "fileSize": 66624,
              "mimeType": "image/jpeg",
              "dimensions": {
                "unit": "px",
                "value": "480x338"
              }
            }
          ]
        }
      },
      {
        "token": {
          "id": "0f73fc5deaf1777eb7451be6df8ac1f723c6d70f5b6e5d1f17b1c3abb0973529",
          "formats": [
            {
              "uri": "ipfs://QmSKptwrz5Jo3KDZvgxZ4nVhp7bzpSatidu4giCZVPTdFd",
              "duration": "00:00:01.920000",
              "fileName": "original.gif",
              "fileSize": 6996943,
              "mimeType": "image/gif",
              "dimensions": {
                "unit": "px",
                "value": "1080x1080"
              }
            },
            {
              "uri": "ipfs://QmWpdiE1FDA1qwxJtCHmtVe3HWfkN5wkU14rNJkBTrHo4N",
              "fileName": "preview_image_1024w.jpg",
              "fileSize": 497528,
              "mimeType": "image/jpeg",
              "dimensions": {
                "unit": "px",
                "value": "1024x1024"
              }
            },
            {
              "uri": "ipfs://QmNocG3cqbHeCgqeS6B6Eyo63PzQQ1gQNvFtrVvasgQbcF",
              "fileName": "preview_image_960w.jpg",
              "fileSize": 431470,
              "mimeType": "image/jpeg",
              "dimensions": {
                "unit": "px",
                "value": "960x960"
              }
            },
            {
              "uri": "ipfs://QmceaxqMKmzGtrEdxRAuTHe6Drdw6me8P4Yb3ymiFAW3Ep",
              "duration": "00:00:01.920000",
              "fileName": "preview_video_480w.mp4",
              "fileSize": 186481,
              "mimeType": "video/mp4",
              "dimensions": {
                "unit": "px",
                "value": "480x480"
              }
            },
            {
              "uri": "ipfs://QmbUZUMuPb9NbgeBEngStpYUDvG6f1JtQLrPT79YZcWE2S",
              "fileName": "preview_image_480w.jpg",
              "fileSize": 89078,
              "mimeType": "image/jpeg",
              "dimensions": {
                "unit": "px",
                "value": "480x480"
              }
            }
          ]
        }
      },
      {
        "token": {
          "id": "69668059a347c9d17b55c84c79b2e15a765597ad6f5901a968e88cc24f1c75e0",
          "formats": [
            {
              "uri": "ipfs://QmaGTwggv9KnWBDUiTBJyguApkmbrcnun546wFckCUVjC9",
              "duration": "00:00:09.880000",
              "fileName": "original.mp4",
              "fileSize": 15910823,
              "mimeType": "video/mp4",
              "dimensions": {
                "unit": "px",
                "value": "1280x960"
              }
            },
            {
              "uri": "ipfs://Qmayz3d785VY97Tky722u4MmETFVr9LFbMrVoEEZaWLZR3",
              "duration": "00:00:09.880000",
              "fileName": "full_video_720h.mp4",
              "fileSize": 6344472,
              "mimeType": "video/mp4",
              "dimensions": {
                "unit": "px",
                "value": "960x720"
              }
            },
            {
              "uri": "ipfs://QmREpCRqnJTKBbJhLeNQU7xXHdN2NbyYJYmNDrXyMLd7oB",
              "duration": "00:00:09.880000",
              "fileName": "preview_video_480w.mp4",
              "fileSize": 1565897,
              "mimeType": "video/mp4",
              "dimensions": {
                "unit": "px",
                "value": "480x360"
              }
            },
            {
              "uri": "ipfs://QmetgUDn8WoAzsMM1jBAcqxPq3SZ3UZe32DjhfLmtoSs6Q",
              "fileName": "preview_image_1280w.jpg",
              "fileSize": 134567,
              "mimeType": "image/jpeg",
              "dimensions": {
                "unit": "px",
                "value": "1280x960"
              }
            },
            {
              "uri": "ipfs://QmYH63g6v6vJ8J5y7f7qpa3Ey6A625QMge8vULNqstG67H",
              "fileName": "preview_image_1024w.jpg",
              "fileSize": 84307,
              "mimeType": "image/jpeg",
              "dimensions": {
                "unit": "px",
                "value": "1024x768"
              }
            },
            {
              "uri": "ipfs://QmZBuU6d7gbn29L3VPRTdkPt8YKUzJp6W5P8QjAjcd1m5A",
              "fileName": "preview_image_960w.jpg",
              "fileSize": 74505,
              "mimeType": "image/jpeg",
              "dimensions": {
                "unit": "px",
                "value": "960x720"
              }
            },
            {
              "uri": "ipfs://QmWf6sioPC8Axi8raKk83maiskdQrKR43aVA63ZDU8T3rY",
              "fileName": "preview_image_480w.jpg",
              "fileSize": 20029,
              "mimeType": "image/jpeg",
              "dimensions": {
                "unit": "px",
                "value": "480x360"
              }
            }
          ]
        }
      }
    ]
  },
  "tokens": [
    {
      "contract": "KT1LjmAdYQCLBjwv4S2oFkEzyHVkomAf5MrW",
      "tokenId": 8125
    },
    {
      "contract": "KT1LjmAdYQCLBjwv4S2oFkEzyHVkomAf5MrW",
      "tokenId": 7935
    },
    {
      "contract": "KT1LjmAdYQCLBjwv4S2oFkEzyHVkomAf5MrW",
      "tokenId": 7571
    },
    {
      "contract": "KT1LjmAdYQCLBjwv4S2oFkEzyHVkomAf5MrW",
      "tokenId": 6357
    },
    {
      "contract": "KT1LjmAdYQCLBjwv4S2oFkEzyHVkomAf5MrW",
      "tokenId": 5624
    },
    {
      "contract": "KT1LjmAdYQCLBjwv4S2oFkEzyHVkomAf5MrW",
      "tokenId": 4131
    },
    {
      "contract": "KT1LjmAdYQCLBjwv4S2oFkEzyHVkomAf5MrW",
      "tokenId": 4120
    },
    {
      "contract": "KT1LjmAdYQCLBjwv4S2oFkEzyHVkomAf5MrW",
      "tokenId": 4028
    },
    {
      "contract": "KT1LjmAdYQCLBjwv4S2oFkEzyHVkomAf5MrW",
      "tokenId": 3844
    },
    {
      "contract": "KT1LjmAdYQCLBjwv4S2oFkEzyHVkomAf5MrW",
      "tokenId": 3596
    },
    {
      "contract": "KT1LjmAdYQCLBjwv4S2oFkEzyHVkomAf5MrW",
      "tokenId": 3496
    },
    {
      "contract": "KT1LjmAdYQCLBjwv4S2oFkEzyHVkomAf5MrW",
      "tokenId": 3418
    },
    {
      "contract": "KT1LjmAdYQCLBjwv4S2oFkEzyHVkomAf5MrW",
      "tokenId": 3322
    },
    {
      "contract": "KT1LjmAdYQCLBjwv4S2oFkEzyHVkomAf5MrW",
      "tokenId": 3163
    },
    {
      "contract": "KT1LjmAdYQCLBjwv4S2oFkEzyHVkomAf5MrW",
      "tokenId": 3158
    },
    {
      "contract": "KT1LjmAdYQCLBjwv4S2oFkEzyHVkomAf5MrW",
      "tokenId": 3146
    },
    {
      "contract": "KT1LjmAdYQCLBjwv4S2oFkEzyHVkomAf5MrW",
      "tokenId": 3135
    },
    {
      "contract": "KT1LjmAdYQCLBjwv4S2oFkEzyHVkomAf5MrW",
      "tokenId": 2997
    },
    {
      "contract": "KT1LjmAdYQCLBjwv4S2oFkEzyHVkomAf5MrW",
      "tokenId": 2976
    },
    {
      "contract": "KT1LjmAdYQCLBjwv4S2oFkEzyHVkomAf5MrW",
      "tokenId": 2915
    }
  ]
}